[
   {
      "ui_sref":"gestionprofils",
      "ui_name":"Gestion_des_utilisateurs"
   },
   {
      "ui_sref":"groupe",
      "ui_name":"Gestion_des_profils"
   },
   {
      "ui_sref":"profilsfermes",
      "ui_name":"Affectation_utilisateur_ferme"
   },
   {
      "ui_sref":"familleculture",
      "ui_name":"Famille_de_culture"
   },
   {
      "ui_sref":"listCulture",
      "ui_name":"Culture"
   },
   {
      "ui_sref":"typeVariete",
      "ui_name":"Type_de_variete"
   },
   {
      "ui_sref":"variete",
      "ui_name":"Variete"
   },
   {
      "ui_sref":"generation",
      "ui_name":"Generation"
   },
   {
      "ui_sref":"Tranche_Age",
      "ui_name":"Tranches_age"
   },
   {
      "ui_sref":"produitgenerale",
      "ui_name":"Produit"
   },
   {
      "ui_sref":"listOperation",
      "ui_name":"Liste_des_Operations"
   },
   {
      "ui_sref":"familleoperations",
      "ui_name":"Famille_operations"
   },
   {
      "ui_sref":"uniteoperation",
      "ui_name":"Unite_operation"
   },
   {
      "ui_sref":"categoriearticle",
      "ui_name":"Categorie_des_articles"
   },
   {
      "ui_sref":"refstadephenologiques",
      "ui_name":"Stades_phenologiques"
   },
   {
      "ui_sref":"intensiteStade",
      "ui_name":"Intensites_du_stade"
   },
   {
      "ui_sref":"Qualite_Stade",
      "ui_name":"Qualites_du_stade"
   },
   {
      "ui_sref":"NiveauConformite",
      "ui_name":"Niveaux_de_conformite"
   },
   {
      "ui_sref":"cible",
      "ui_name":"Cibles"
   },
   {
      "ui_sref":"NiveauAttaque",
      "ui_name":"Niveau_des_attaques"
   },
   {
      "ui_sref":"RepartitionAttaque",
      "ui_name":"Niveaux_de_risque"
   },
   {
      "ui_sref":"LieuElimination",
      "ui_name":"Lieux_elimination"
   },
   {
      "ui_sref":"ModeApplication",
      "ui_name":"refModeApplication"
   },
   {
      "ui_sref":"carence",
      "ui_name":"Niveaux_de_carence"
   },
   {
      "ui_sref":"elementsMineraux",
      "ui_name":"Elements_mineraux"
   },
   {
      "ui_sref":"coloration",
      "ui_name":"Niveaux_de_coloration"
   },
   {
      "ui_sref":"fermeteFruit",
      "ui_name":"fermete_fruit"
   },
   {
      "ui_sref":"fermetePeau",
      "ui_name":"fermete_peau"
   },
   {
      "ui_sref":"parametretechnique",
      "ui_name":"Technique"
   },
   {
      "ui_sref":"gestiondessocietes",
      "ui_name":"gestion_societe"
   },
   {
      "ui_sref":"gestiondesfermes",
      "ui_name":"gestion_ferme"
   },
   {
      "ui_sref":"businessunit",
      "ui_name":"Gestion_Business_Unit"
   },
   {
      "ui_sref":"gestionPays",
      "ui_name":"gestionPays"
   },
   {
      "ui_sref":"assolement_parcel_physique",
      "ui_name":"parcelles_physique"
   },
   {
      "ui_sref":"assolement_parcel_culturale",
      "ui_name":"parcelles_culturales"
   },
   {
      "ui_sref":"secteur_irrigation",
      "ui_name":"secteurs_irrigation"
   },
   {
      "ui_sref":"parcelleculturalgroupeoperationnel",
      "ui_name":"groupes_operationnels"
   },
   {
      "ui_sref":"assolement_cycle_cultural",
      "ui_name":"cycles_culturaux"
   },
   {
      "ui_sref":"RefArbre",
      "ui_name":"gestion_arbre"
   },
   {
      "ui_sref":"previsiontoday",
      "ui_name":"Previsions_today"
   },
   {
      "ui_sref":"previsiondemain",
      "ui_name":"prevision_tomorrow"
   },
   {
      "ui_sref":"production_realisee",
      "ui_name":"production_realisee"
   },
   {
      "ui_sref":"actualisation_demande",
      "ui_name":"actualisation_demande"
   },
   {
      "ui_sref":"previsionsAnnuelle",
      "ui_name":"Previsions_annuelle"
   },
   {
      "ui_sref":"multiperiodevariete",
      "ui_name":"analyse_multi_periode_variete"
   },
   {
      "ui_sref":"prevision_journaliere",
      "ui_name":"Prevision_journaliere"
   },
   {
      "ui_sref":"reporting_assolement",
      "ui_name":"assolement"
   },
   {
      "ui_sref":"suivi_hebdo_prevu_realise",
      "ui_name":"Suivi_hebdo_prevu_realise"
   },
   {
      "ui_sref":"periodeestimation",
      "ui_name":"parametrage_periodes_estimations"
   },
   {
      "ui_sref":"notif_manuel",
      "ui_name":"notif_manuel"
   },
   {
      "ui_sref":"notif_auto",
      "ui_name":"notif_auto"
   },
   {
      "ui_sref":"ouvriers",
      "ui_name":"Ouvriers"
   },
   {
      "ui_sref":"salaries",
      "ui_name":"Salaries"
   },
   {
      "ui_sref":"stadePheno",
      "ui_name":"Suivi_stades"
   },
   {
      "ui_sref":"pourcentageOuverture",
      "ui_name":"Pourcentage_ouverture"
   },
   {
      "ui_sref":"intensiteFleurs",
      "ui_name":"Intensite_fleurs"
   },
   {
      "ui_sref":"ressources_hydriques",
      "ui_name":"ressources_hydriques"
   },
   {
      "ui_sref":"suivimeteo",
      "ui_name":"Suivi_meteo"
   },
   {
      "ui_sref":"apportEau",
      "ui_name":"Apport_en_eau"
   },
   {
      "ui_sref":"testConf",
      "ui_name":"Test_de_conformité"
   },
   {
      "ui_sref":"aspectVegetal",
      "ui_name":"Aspect_vegetal"
   },
   {
      "ui_sref":"solutionmere",
      "ui_name":"Solution_mere"
   },
   {
      "ui_sref":"programmefertilisation",
      "ui_name":"Programme_de_fertilisation"
   },
   {
      "ui_sref":"ordrefertlisation",
      "ui_name":"Fertlisation"
   },
   {
      "ui_sref":"controlephec",
      "ui_name":"Controle_EC"
   },
   {
      "ui_sref":"observationphyto",
      "ui_name":"Observation_phyto"
   },
   {
      "ui_sref":"comptagedesravageurs",
      "ui_name":"Comptage_des_ravageur"
   },
   {
      "ui_sref":"comptagePiege",
      "ui_name":"Comptage_piegeage"
   },
   {
      "ui_sref":"ordretraitementphytosanitaire",
      "ui_name":"Traitement_phyto"
   },
   {
      "ui_sref":"ramassageDestruction",
      "ui_name":"Ramassage_destructions_fruits"
   },
   {
      "ui_sref":"piquressurfruits",
      "ui_name":"piqure_fruit"
   },
   {
      "ui_sref":"changementpheromone",
      "ui_name":"changement_phero"
   },
   {
      "ui_sref":"Piege",
      "ui_name":"codification_pieges"
   },
   {
      "ui_sref":"visites",
      "ui_name":"Visites"
   },
   {
      "ui_sref":"gestionprofils",
      "ui_name":"Gestion des utilisateurs"
   },
   {
      "ui_sref":"profilsfermes",
      "ui_name":"Affectation utilisateur/ferme"
   },
   {
      "ui_sref":"gestiondesfermes",
      "ui_name":"Gestion des ferme"
   },
   {
      "ui_sref":"assolement_parcel_culturale",
      "ui_name":"Gestion parcelles culturales"
   },
   {
      "ui_sref":"tableaudebord_prevision",
      "ui_name":"Dashbord"
   },
   {
      "ui_sref":"notif_manuel",
      "ui_name":"Notifications manuelles"
   },
   {
      "ui_sref":"actualisation_demande",
      "ui_name":"Actualisation à la demande"
   },
   {
      "ui_sref":"TB_technique",
      "ui_name":"Dashbord"
   },
   {
      "ui_sref":"suivimeteo",
      "ui_name":"Suivi météo"
   },
   {
      "ui_sref":"observationphyto",
      "ui_name":"Observation phytosanitaire"
   },
   {
      "ui_sref":"tb_covid19",
      "ui_name":"Dashboard"
   }
]
